nosqlite.py
setup.py
nosqlite.egg-info/PKG-INFO
nosqlite.egg-info/SOURCES.txt
nosqlite.egg-info/dependency_links.txt
nosqlite.egg-info/top_level.txt