Metadata-Version: 1.1
Name: nosqlite
Version: 0.0.3
Summary: A wrapper for sqlite3 to have schemaless, document-store features
Home-page: https://github.com/shaunduncan/nosqlite
Author: Shaun Duncan
Author-email: shaun.duncan@gmail.com
License: MIT
Keywords: nosql sqlite nosqlite
Platform: UNKNOWN
Classifier: Development Status :: 3 - Alpha
Classifier: License :: OSI Approved :: MIT License
Classifier: Operating System :: OS Independent
Classifier: Programming Language :: Python
Classifier: Programming Language :: Python :: 2
Classifier: Programming Language :: Python :: 2.6
Classifier: Programming Language :: Python :: 2.7
Classifier: Programming Language :: Python :: 3
Classifier: Programming Language :: Python :: 3.3
Classifier: Programming Language :: Python :: 3.4
Classifier: Topic :: Software Development :: Libraries :: Python Modules
